nuclearacids/__init__.py
nuclearacids/_version.py
nuclearacids-0.0.0.dist-info/LICENSE
nuclearacids-0.0.0.dist-info/METADATA
nuclearacids-0.0.0.dist-info/WHEEL
nuclearacids-0.0.0.dist-info/top_level.txt
nuclearacids-0.0.0.dist-info/RECORD
