Metadata-Version: 2.1
Name: nuclearacids
Version: 0.0.0
Summary: Nuclear Acids
Author-email: Zhiyuan Chen <this@zyc.ai>
Maintainer-email: Zhiyuan Chen <this@zyc.ai>
License: GNU AFFERO GENERAL PUBLIC LICENSE
Project-URL: documentation, http://nuclearacids.danling.org
Project-URL: homepage, http://nuclearacids.danling.org
Project-URL: repository, https://github.com/multimolecule/nuclearacids
Keywords: DNA,RNA,Protein
Classifier: Development Status :: 2 - Pre-Alpha
Classifier: Intended Audience :: Developers
Classifier: Intended Audience :: Education
Classifier: Intended Audience :: Science/Research
Classifier: Operating System :: OS Independent
Classifier: Programming Language :: Python :: 3 :: Only
Classifier: Programming Language :: Python :: 3.7
Classifier: Programming Language :: Python :: 3.8
Classifier: Programming Language :: Python :: 3.9
Classifier: Programming Language :: Python :: 3.10
Classifier: Programming Language :: Python :: 3.11
Classifier: Programming Language :: Python :: 3.12
Classifier: Topic :: Scientific/Engineering :: Artificial Intelligence
Classifier: Topic :: Scientific/Engineering :: Bio-Informatics
Classifier: License :: OSI Approved :: GNU Affero General Public License v3 or later (AGPLv3+)
Requires-Python: >=3
License-File: LICENSE
Requires-Dist: accelerate
Requires-Dist: chanfig
Requires-Dist: danling
Requires-Dist: multimolecule
Requires-Dist: einops
